Workbook

Sheet Master Prices
A2: Ingredient ID | B2: Ingredient | C2: Rate ₹/kg | D2: Category / Notes
A3: RM-001 | B3: Whole Wheat (Sharbati Gehu) | C3: 35 | D3: Base Grain
A4: RM-002 | B4: Normal Jau | C4: 50 | D4: Standard Grain
A5: RM-003 | B5: Premium Jau | C5: 70 | D5: Premium Grain
A6: RM-004 | B6: Standard Desi Kala Chana | C6: 80 | D6: Standard Pulse
A7: RM-005 | B7: Premium Desi Kala Chana | C7: 100 | D7: Premium Pulse
A8: RM-006 | B8: Soybean | C8: 120 | D8: High-Protein Legume
A9: RM-007 | B9: Jundhi (Jowar) | C9: 100 | D9: Millet
A10: RM-008 | B10: Ragi | C10: 70 | D10: Millet
A11: RM-009 | B11: Bajra | C11: 40 | D11: Millet
A12: RM-010 | B12: Flaxseed (Alsi) | C12: 150 | D12: Oilseed / Omega-3
A13: RM-011 | B13: Psyllium Husk (Isabgol) | C13: 150 | D13: Soluble Fiber
A14: RM-012 | B14: Kuttu (Buckwheat) | C14: 120 | D14: Gluten-Free Grain
... A22: OP-003 | B22: Delivery cost | C22: 50 | D22: per packet
A26: HSN Code: 11010000

Sheet Nutrient Reference
A2: Ingredient | B2: Energy kcal | C2: Protein g | D2: Carbohydrates g | E2: Sugars g | F2: Fat g | G2: Sat Fat g | H2: Fibre g | I2: Sodium mg | J2: Data Status
A3: Whole Wheat (Sharbati Gehu) | B3: 340 | C3: 12 | D3: 71 | E3: 0.4 | F3: 1.5 | G3: 0.3 | H3: 11.5 | I3: 2 | J3: Provided
A4: Normal Jau | B4: 354 | C4: 12 | D4: 73 | E4: 0.8 | F4: 2.3 | G4: 0.5 | H4: 17 | I4: 12 | J4: Provided
A5: Premium Jau | B5: 354 | C5: 12.5 | D5: 73 | E5: 0.8 | F5: 2.3 | G5: 0.5 | H5: 17.5 | I5: 12 | J5: Provided
A6: Standard Desi Kala Chana | B6: 360 | C6: 20 | D6: 60 | E6: 2.5 | F6: 5 | G6: 0.6 | H6: 17 | I6: 24 | J6: Provided
A7: Premium Desi Kala Chana | B7: 360 | C7: 21 | D7: 59 | E7: 2.5 | F7: 5.2 | G7: 0.6 | H7: 18 | I7: 24 | J7: Provided
A8: Soybean | B8: 446 | C8: 36 | D8: 30 | E8: 7 | F8: 20 | G8: 2.8 | H8: 9 | I8: 2 | J8: Provided
A9: Jundhi (Jowar) | B9: 349 | C9: 10.4 | D9: 72 | E9: 1.2 | F9: 3.3 | G9: 0.7 | H9: 10 | I9: 6 | J9: Provided
A10: Ragi | B10: 328 | C10: 7.3 | D10: 72 | E10: 0.6 | F10: 1.3 | G10: 0.3 | H10: 11.5 | I10: 11 | J10: Provided
A11: Bajra | B11: 361 | C11: 11.6 | D11: 67 | E11: 0.5 | F11: 5 | G11: 0.9 | H11: 11.3 | I11: 10 | J11: Provided
A12: Flaxseed (Alsi) | B12: 534 | C12: 18 | D12: 29 | E12: 1.5 | F12: 42 | G12: 3.7 | H12: 27 | I12: 30 | J12: Provided
A13: Psyllium Husk (Isabgol) | B13: 189 | C13: 0 | D13: 89 | E13: 0 | F13: 0.5 | G13: 0.1 | H13: 78 | I13: 100 | J13: Provided
A14: Kuttu (Buckwheat) | B14: 343 | C14: 13.3 | D14: 71.5 | E14: 1.5 | F14: 3.4 | G14: 0.7 | H14: 10 | I14: 1 | J14: Provided
... A18: Sunflower Seeds | B18: 584 | C18: 20.8 | D18: 20 | E18: 2.6 | F18: 51.5 | G18: 4.5 | H18: 8.6 | I18: 9 | J18: Provided

Sheet Everyday Atta
A1: Ingredient | B1: Ratio % | C1: 5 kg Qty | D1: 10 kg Qty | E1: Rate ₹/kg | F1: Cost — 5 kg | G1: Cost — 10 kg
A2: Whole Wheat (Sharbati Gehu) | B2: 0.75 | C2: =B2*5 -> 3.75 | D2: =B2*10 -> 7.5 | E2: {=IFERROR(_xlfn.XLOOKUP(A2,tblPrices[Ingredient],tblPrices[Rate ₹/kg],0),0)} -> 35 | F2: =C2*E2 -> 131.25 | G2: =D2*E2 -> 262.5 | I2: Metric | J2: Estimated Value | K2: Unit | L2: Note
A3: Standard Desi Kala Chana | B3: 0.08 | C3: =B3*5 -> 0.4 | D3: =B3*10 -> 0.8 | E3: {=IFERROR(_xlfn.XLOOKUP(A3,tblPrices[Ingredient],tblPrices[Rate ₹/kg],0),0)} -> 80 | F3: =C3*E3 -> 32 | G3: =D3*E3 -> 64 | I3: Energy (kcal) | J3: {=IFERROR(SUMPRODUCT($B$2:$B$9,_xlfn.XLOOKUP($A$2:$A$9,tblNutrients[Ingredient],tblNutrients[Energy kcal],0)),0)} -> 348.93 | K3: kcal | L3: Uses available reference data
A4: Normal Jau | B4: 0.05 | C4: =B4*5 -> 0.25 | D4: =B4*10 -> 0.5 | E4: {=IFERROR(_xlfn.XLOOKUP(A4,tblPrices[Ingredient],tblPrices[Rate ₹/kg],0),0)} -> 50 | F4: =C4*E4 -> 12.5 | G4: =D4*E4 -> 25 | I4: Protein (g) | J4: {=IFERROR(SUMPRODUCT($B$2:$B$9,_xlfn.XLOOKUP($A$2:$A$9,tblNutrients[Ingredient],tblNutrients[Protein g],0)),0)} -> 13.51 | K4: g | L4: Uses available reference data
A5: Soybean | B5: 0.04 | C5: =B5*5 -> 0.2 | D5: =B5*10 -> 0.4 | E5: {=IFERROR(_xlfn.XLOOKUP(A5,tblPrices[Ingredient],tblPrices[Rate ₹/kg],0),0)} -> 120 | F5: =C5*E5 -> 24 | G5: =D5*E5 -> 48 | I5: Carbohydrates (g) | J5: {=IFERROR(SUMPRODUCT($B$2:$B$9,_xlfn.XLOOKUP($A$2:$A$9,tblNutrients[Ingredient],tblNutrients[Carbohydrates g],0)),0)} -> 68.13 | K5: g | L5: Uses available reference data
A6: Jundhi (Jowar) | B6: 0.03 | C6: =B6*5 -> 0.15 | D6: =B6*10 -> 0.3 | E6: {=IFERROR(_xlfn.XLOOKUP(A6,tblPrices[Ingredient],tblPrices[Rate ₹/kg],0),0)} -> 100 | F6: =C6*E6 -> 15 | G6: =D6*E6 -> 30 | I6: Total Sugars (g) | J6: {=IFERROR(SUMPRODUCT($B$2:$B$9,_xlfn.XLOOKUP($A$2:$A$9,tblNutrients[Ingredient],tblNutrients[Sugars g],0)),0)} -> 0.893 | K6: g | L6: Uses available reference data
A7: Ragi | B7: 0.02 | C7: =B7*5 -> 0.1 | D7: =B7*10 -> 0.2 | E7: {=IFERROR(_xlfn.XLOOKUP(A7,tblPrices[Ingredient],tblPrices[Rate ₹/kg],0),0)} -> 70 | F7: =C7*E7 -> 7 | G7: =D7*E7 -> 14 | I7: Added Sugars (g) | J7: =0 -> 0 | K7: g | L7: Assumed zero
A8: Bajra | B8: 0.02 | C8: =B8*5 -> 0.1 | D8: =B8*10 -> 0.2 | E8: {=IFERROR(_xlfn.XLOOKUP(A8,tblPrices[Ingredient],tblPrices[Rate ₹/kg],0),0)} -> 40 | F8: =C8*E8 -> 4 | G8: =D8*E8 -> 8 | I8: Total Fat (g) | J8: {=IFERROR(SUMPRODUCT($B$2:$B$9,_xlfn.XLOOKUP($A$2:$A$9,tblNutrients[Ingredient],tblNutrients[Fat g],0)),0)} -> 3.085 | K8: g | L8: Uses available reference data
A9: Flaxseed (Alsi) | B9: 0.01 | C9: =B9*5 -> 0.05 | D9: =B9*10 -> 0.1 | E9: {=IFERROR(_xlfn.XLOOKUP(A9,tblPrices[Ingredient],tblPrices[Rate ₹/kg],0),0)} -> 150 | F9: =C9*E9 -> 7.5 | G9: =D9*E9 -> 15 | I9: Saturated Fat (g) | J9: {=IFERROR(SUMPRODUCT($B$2:$B$9,_xlfn.XLOOKUP($A$2:$A$9,tblNutrients[Ingredient],tblNutrients[Sat Fat g],0)),0)} -> 0.492 | K9: g | L9: Uses available reference data
A10: Total Raw Material | B10: =SUM(B2:B9) -> 1 | C10: =SUM(C2:C9) -> 5 | D10: =SUM(D2:D9) -> 10 | F10: =SUM(F2:F9) -> 233.25 | G10: =SUM(G2:G9) -> 466.5 | I10: Trans Fat (g) | J10: =0 -> 0 | K10: g | L10: Assumed zero
A11: Milling & Roasting | E11: {=_xlfn.XLOOKUP("Milling & Roasting Cost",tblPrices[Ingredient],tblPrices[Rate ₹/kg],0)} -> 4 | F11: =5*E11 -> 20 | G11: =10*E11 -> 40 | I11: Dietary Fibre (g) | J11: {=IFERROR(SUMPRODUCT($B$2:$B$9,_xlfn.XLOOKUP($A$2:$A$9,tblNutrients[Ingredient],tblNutrients[Fibre g],0)),0)} -> 12.221 | K11: g | L11: Uses available reference data
A12: Pouch Packaging | E12: {=_xlfn.XLOOKUP("3-Layer Laminated Pouch",tblPrices[Ingredient],tblPrices[Rate ₹/kg],0)} -> 5 | F12: =5*E12 -> 25 | G12: =10*E12 -> 50 | I12: Sodium (mg) | J12: {=IFERROR(SUMPRODUCT($B$2:$B$9,_xlfn.XLOOKUP($A$2:$A$9,tblNutrients[Ingredient],tblNutrients[Sodium mg],0)),0)} -> 5 | K12: mg | L12: Uses available reference data
A13: Total Production Cost | E13: =SUM(Ingredient_1[Rate ₹/kg]) -> 654 | F13: =SUM(F10:F12) -> 278.25 | G13: =SUM(G10:G12) -> 556.5 | I13: Cholesterol (mg) | J13: =0 -> 0 | K13: mg | L13: Assumed zero
A16: Metric | B16: 1 kg Pack | C16: 5 kg Pack | D16: 10 kg Pack | E16: Notes
A17: Total Production Cost | B17: =G13/10 -> 55.65 | C17: =F13 -> 278.25 | D17: =G13 -> 556.5 | E17: Linked to recipe cost
A18: Retail Price (MRP) | B18: =D18/10 -> 95 | C18: =D18/2 -> 475 | D18: 950 | E18: Input: 10 kg MRP
A19: Wholesale Price | B19: =D19/10 -> 76 | C19: =D19/2 -> 380 | D19: 760 | E19: Input: 10 kg wholesale
A20: Direct Profit | B20: =B18-B17 -> 39.35 | C20: =C18-C17 -> 196.75 | D20: =D18-D17 -> 393.5 | E20: MRP less cost
A21: Wholesale Profit | B21: =B19-B17 -> 20.35 | C21: =C19-C17 -> 101.75 | D21: =D19-D17 -> 203.5 | E21: Wholesale less cost
A22: Direct Margin % | B22: =SUM(Pricing_Profit_Analysis_1[1 kg Pack]) -> 286.35 | C22: =SUM(Pricing_Profit_Analysis_1[5 kg Pack]) -> 1431.75 | D22: =IFERROR(D20/D18,0) -> 0.41421053 | E22: Direct profit / MRP

Sheet Sugar Care
A1: Ingredient | B1: Ratio % | C1: 5 kg Qty | D1: 10 kg Qty | E1: Rate ₹/kg | F1: Cost — 5 kg | G1: Cost — 10 kg
C2: =B2*5 -> 0 | D2: =B2*10 -> 0 | E2: {=IFERROR(_xlfn.XLOOKUP(A2,tblPrices[Ingredient],tblPrices[Rate ₹/kg],0),0)} -> 0 | F2: =C2*E2 -> 0 | G2: =D2*E2 -> 0
A3: Whole Wheat (Sharbati Gehu) | B3: 0.5 | C3: =B3*5 -> 2.5 | D3: =B3*10 -> 5 | E3: {=IFERROR(_xlfn.XLOOKUP(A3,tblPrices[Ingredient],tblPrices[Rate ₹/kg],0),0)} -> 35 | F3: =C3*E3 -> 87.5 | G3: =D3*E3 -> 175 | I3: Metric | J3: Estimated Value | K3: Unit | L3: Note
A4: Premium Jau | B4: 0.15 | C4: =B4*5 -> 0.75 | D4: =B4*10 -> 1.5 | E4: {=IFERROR(_xlfn.XLOOKUP(A4,tblPrices[Ingredient],tblPrices[Rate ₹/kg],0),0)} -> 70 | F4: =C4*E4 -> 52.5 | G4: =D4*E4 -> 105 | I4: Energy (kcal) | J4: {=IFERROR(SUMPRODUCT($B$3:$B$10,_xlfn.XLOOKUP($A$3:$A$10,tblNutrients[Ingredient],tblNutrients[Energy kcal],0)),0)} -> 356.18 | K4: kcal | L4: Uses available reference data
A5: Premium Desi Kala Chana | B5: 0.1 | C5: =B5*5 -> 0.5 | D5: =B5*10 -> 1 | E5: {=IFERROR(_xlfn.XLOOKUP(A5,tblPrices[Ingredient],tblPrices[Rate ₹/kg],0),0)} -> 100 | F5: =C5*E5 -> 50 | G5: =D5*E5 -> 100 | I5: Protein (g) | J5: {=IFERROR(SUMPRODUCT($B$3:$B$10,_xlfn.XLOOKUP($A$3:$A$10,tblNutrients[Ingredient],tblNutrients[Protein g],0)),0)} -> 13.976 | K5: g | L5: Uses available reference data
A6: Jundhi (Jowar) | B6: 0.08 | C6: =B6*5 -> 0.4 | D6: =B6*10 -> 0.8 | E6: {=IFERROR(_xlfn.XLOOKUP(A6,tblPrices[Ingredient],tblPrices[Rate ₹/kg],0),0)} -> 100 | F6: =C6*E6 -> 40 | G6: =D6*E6 -> 80 | I6: Carbohydrates (g) | J6: {=IFERROR(SUMPRODUCT($B$3:$B$10,_xlfn.XLOOKUP($A$3:$A$10,tblNutrients[Ingredient],tblNutrients[Carbohydrates g],0)),0)} -> 66.76 | K6: g | L6: Uses available reference data
A7: Soybean | B7: 0.05 | C7: =B7*5 -> 0.25 | D7: =B7*10 -> 0.5 | E7: {=IFERROR(_xlfn.XLOOKUP(A7,tblPrices[Ingredient],tblPrices[Rate ₹/kg],0),0)} -> 120 | F7: =C7*E7 -> 30 | G7: =D7*E7 -> 60 | I7: Total Sugars (g) | J7: {=IFERROR(SUMPRODUCT($B$3:$B$10,_xlfn.XLOOKUP($A$3:$A$10,tblNutrients[Ingredient],tblNutrients[Sugars g],0)),0)} -> 1.111 | K7: g | L7: Uses available reference data
A8: Ragi | B8: 0.05 | C8: =B8*5 -> 0.25 | D8: =B8*10 -> 0.5 | E8: {=IFERROR(_xlfn.XLOOKUP(A8,tblPrices[Ingredient],tblPrices[Rate ₹/kg],0),0)} -> 70 | F8: =C8*E8 -> 17.5 | G8: =D8*E8 -> 35 | I8: Added Sugars (g) | J8: =0 -> 0 | K8: g | L8: Assumed zero
A9: Bajra | B9: 0.04 | C9: =B9*5 -> 0.2 | D9: =B9*10 -> 0.4 | E9: {=IFERROR(_xlfn.XLOOKUP(A9,tblPrices[Ingredient],tblPrices[Rate ₹/kg],0),0)} -> 40 | F9: =C9*E9 -> 8 | G9: =D9*E9 -> 16 | I9: Total Fat (g) | J9: {=IFERROR(SUMPRODUCT($B$3:$B$10,_xlfn.XLOOKUP($A$3:$A$10,tblNutrients[Ingredient],tblNutrients[Fat g],0)),0)} -> 4.404 | K9: g | L9: Uses available reference data
A10: Flaxseed (Alsi) | B10: 0.03 | C10: =B10*5 -> 0.15 | D10: =B10*10 -> 0.3 | E10: {=IFERROR(_xlfn.XLOOKUP(A10,tblPrices[Ingredient],tblPrices[Rate ₹/kg],0),0)} -> 150 | F10: =C10*E10 -> 22.5 | G10: =D10*E10 -> 45 | I10: Saturated Fat (g) | J10: {=IFERROR(SUMPRODUCT($B$3:$B$10,_xlfn.XLOOKUP($A$3:$A$10,tblNutrients[Ingredient],tblNutrients[Sat Fat g],0)),0)} -> 0.643 | K10: g | L10: Uses available reference data
A11: Total Raw Material | B11: =SUM(B3:B10) -> 1 | C11: =SUM(C3:C10) -> 5 | D11: =SUM(D3:D10) -> 10 | F11: =SUM(F3:F10) -> 308 | G11: =SUM(G3:G10) -> 616 | I11: Trans Fat (g) | J11: =0 -> 0 | K11: g | L11: Assumed zero
A12: Milling & Roasting | E12: {=_xlfn.XLOOKUP("Milling & Roasting Cost",tblPrices[Ingredient],tblPrices[Rate ₹/kg],0)} -> 4 | F12: =5*E12 -> 20 | G12: =10*E12 -> 40 | I12: Dietary Fibre (g) | J12: {=IFERROR(SUMPRODUCT($B$3:$B$10,_xlfn.XLOOKUP($A$3:$A$10,tblNutrients[Ingredient],tblNutrients[Fibre g],0)),0)} -> 13.262 | K12: g | L12: Uses available reference data
A13: Pouch Packaging | E13: {=_xlfn.XLOOKUP("3-Layer Laminated Pouch",tblPrices[Ingredient],tblPrices[Rate ₹/kg],0)} -> 5 | F13: =5*E13 -> 25 | G13: =10*E13 -> 50 | I13: Sodium (mg) | J13: {=IFERROR(SUMPRODUCT($B$3:$B$10,_xlfn.XLOOKUP($A$3:$A$10,tblNutrients[Ingredient],tblNutrients[Sodium mg],0)),0)} -> 7.63 | K13: mg | L13: Uses available reference data
A14: Total Production Cost | E14: =SUM(Ingredient_2[Rate ₹/kg]) -> 694 | F14: =SUM(F11:F13) -> 353 | G14: =SUM(G11:G13) -> 706 | I14: Cholesterol (mg) | J14: =0 -> 0 | K14: mg | L14: Assumed zero
A17: Metric | B17: 1 kg Pack | C17: 5 kg Pack | D17: 10 kg Pack | E17: Notes
A18: Total Production Cost | B18: =G14/10 -> 70.6 | C18: =F14 -> 353 | D18: =G14 -> 706 | E18: Linked to recipe cost
A19: Retail Price (MRP) | B19: =D19/10 -> 125 | C19: =D19/2 -> 625 | D19: 1250 | E19: Input: 10 kg MRP
A20: Wholesale Price | B20: =D20/10 -> 100 | C20: =D20/2 -> 500 | D20: 1000 | E20: Input: 10 kg wholesale
A21: Direct Profit | B21: =B19-B18 -> 54.4 | C21: =C19-C18 -> 272 | D21: =D19-D18 -> 544 | E21: MRP less cost
A22: Wholesale Profit | B22: =B20-B18 -> 29.4 | C22: =C20-C18 -> 147 | D22: =D20-D18 -> 294 | E22: Wholesale less cost
A23: Direct Margin % | B23: =SUM(Pricing_Profit_Analysis_2[1 kg Pack]) -> 379.4 | C23: =SUM(Pricing_Profit_Analysis_2[5 kg Pack]) -> 1897 | D23: =IFERROR(D21/D19,0) -> 0.4352 | E23: Direct profit / MRP

Sheet Thyro Care
A1: Ingredient | B1: Ratio % | C1: 5 kg Qty | D1: 10 kg Qty | E1: Rate ₹/kg | F1: Cost — 5 kg | G1: Cost — 10 kg
C2: =B2*5 -> 0 | D2: =B2*10 -> 0 | E2: {=IFERROR(_xlfn.XLOOKUP(A2,tblPrices[Ingredient],tblPrices[Rate ₹/kg],0),0)} -> 0 | F2: =C2*E2 -> 0 | G2: =D2*E2 -> 0
A3: Kuttu (Buckwheat) | B3: 0.4 | C3: =B3*5 -> 2 | D3: =B3*10 -> 4 | E3: {=IFERROR(_xlfn.XLOOKUP(A3,tblPrices[Ingredient],tblPrices[Rate ₹/kg],0),0)} -> 120 | F3: =C3*E3 -> 240 | G3: =D3*E3 -> 480 | I3: Metric | J3: Estimated Value | K3: Unit | L3: Note
A4: Jundhi (Jowar) | B4: 0.25 | C4: =B4*5 -> 1.25 | D4: =B4*10 -> 2.5 | E4: {=IFERROR(_xlfn.XLOOKUP(A4,tblPrices[Ingredient],tblPrices[Rate ₹/kg],0),0)} -> 100 | F4: =C4*E4 -> 125 | G4: =D4*E4 -> 250 | I4: Energy (kcal) | J4: {=IFERROR(SUMPRODUCT($B$3:$B$8,_xlfn.XLOOKUP($A$3:$A$8,tblNutrients[Ingredient],tblNutrients[Energy kcal],0)),0)} -> 360.3 | K4: kcal | L4: Uses available reference data
A5: Moong Dal (Yellow) | B5: 0.15 | C5: =B5*5 -> 0.75 | D5: =B5*10 -> 1.5 | E5: {=IFERROR(_xlfn.XLOOKUP(A5,tblPrices[Ingredient],tblPrices[Rate ₹/kg],0),0)} -> 110 | F5: =C5*E5 -> 82.5 | G5: =D5*E5 -> 165 | I5: Protein (g) | J5: {=IFERROR(SUMPRODUCT($B$3:$B$8,_xlfn.XLOOKUP($A$3:$A$8,tblNutrients[Ingredient],tblNutrients[Protein g],0)),0)} -> 13.96 | K5: g | L5: Uses available reference data
A6: Ragi | B6: 0.1 | C6: =B6*5 -> 0.5 | D6: =B6*10 -> 1 | E6: {=IFERROR(_xlfn.XLOOKUP(A6,tblPrices[Ingredient],tblPrices[Rate ₹/kg],0),0)} -> 70 | F6: =C6*E6 -> 35 | G6: =D6*E6 -> 70 | I6: Carbohydrates (g) | J6: {=IFERROR(SUMPRODUCT($B$3:$B$8,_xlfn.XLOOKUP($A$3:$A$8,tblNutrients[Ingredient],tblNutrients[Carbohydrates g],0)),0)} -> 66.745 | K6: g | L6: Uses available reference data
A7: Chia Seeds | B7: 0.05 | C7: =B7*5 -> 0.25 | D7: =B7*10 -> 0.5 | E7: {=IFERROR(_xlfn.XLOOKUP(A7,tblPrices[Ingredient],tblPrices[Rate ₹/kg],0),0)} -> 250 | F7: =C7*E7 -> 62.5 | G7: =D7*E7 -> 125 | I7: Total Sugars (g) | J7: {=IFERROR(SUMPRODUCT($B$3:$B$8,_xlfn.XLOOKUP($A$3:$A$8,tblNutrients[Ingredient],tblNutrients[Sugars g],0)),0)} -> 1.375 | K7: g | L7: Uses available reference data
A8: Flaxseed (Alsi) | B8: 0.05 | C8: =B8*5 -> 0.25 | D8: =B8*10 -> 0.5 | E8: {=IFERROR(_xlfn.XLOOKUP(A8,tblPrices[Ingredient],tblPrices[Rate ₹/kg],0),0)} -> 150 | F8: =C8*E8 -> 37.5 | G8: =D8*E8 -> 75 | I8: Added Sugars (g) | J8: =0 -> 0 | K8: g | L8: Assumed zero
A9: Total Raw Material | B9: =SUM(B3:B8) -> 1 | C9: =SUM(C3:C8) -> 5 | D9: =SUM(D3:D8) -> 10 | F9: =SUM(F3:F8) -> 582.5 | G9: =SUM(G3:G8) -> 1165 | I9: Total Fat (g) | J9: {=IFERROR(SUMPRODUCT($B$3:$B$8,_xlfn.XLOOKUP($A$3:$A$8,tblNutrients[Ingredient],tblNutrients[Fat g],0)),0)} -> 6.13 | K9: g | L9: Uses available reference data
A10: Milling & Roasting | E10: {=_xlfn.XLOOKUP("Milling & Roasting Cost",tblPrices[Ingredient],tblPrices[Rate ₹/kg],0)} -> 4 | F10: =5*E10 -> 20 | G10: =10*E10 -> 40 | I10: Saturated Fat (g) | J10: {=IFERROR(SUMPRODUCT($B$3:$B$8,_xlfn.XLOOKUP($A$3:$A$8,tblNutrients[Ingredient],tblNutrients[Sat Fat g],0)),0)} -> 0.88 | K10: g | L10: Uses available reference data
A11: Pouch Packaging | E11: {=_xlfn.XLOOKUP("3-Layer Laminated Pouch",tblPrices[Ingredient],tblPrices[Rate ₹/kg],0)} -> 5 | F11: =5*E11 -> 25 | G11: =10*E11 -> 50 | I11: Trans Fat (g) | J11: =0 -> 0 | K11: g | L11: Assumed zero
A12: Total Production Cost | E12: =SUM(Ingredient_3[Rate ₹/kg]) -> 809 | F12: =SUM(F9:F11) -> 627.5 | G12: =SUM(G9:G11) -> 1255 | I12: Dietary Fibre (g) | J12: {=IFERROR(SUMPRODUCT($B$3:$B$8,_xlfn.XLOOKUP($A$3:$A$8,tblNutrients[Ingredient],tblNutrients[Fibre g],0)),0)} -> 13.165 | K12: g | L12: Uses available reference data
I13: Sodium (mg) | J13: {=IFERROR(SUMPRODUCT($B$3:$B$8,_xlfn.XLOOKUP($A$3:$A$8,tblNutrients[Ingredient],tblNutrients[Sodium mg],0)),0)} -> 7.55 | K13: mg | L13: Uses available reference data
I14: Cholesterol (mg) | J14: =0 -> 0 | K14: mg | L14: Assumed zero
A18: Metric | B18: 1 kg Pack | C18: 5 kg Pack | D18: 10 kg Pack | E18: Notes
A19: Total Production Cost | B19: =G12/10 -> 125.5 | C19: =F12 -> 627.5 | D19: =G12 -> 1255 | E19: Linked to recipe cost
A20: Retail Price (MRP) | B20: =D20/10 -> 165 | C20: =D20/2 -> 825 | D20: 1650 | E20: Input: 10 kg MRP
A21: Wholesale Price | B21: =D21/10 -> 135 | C21: =D21/2 -> 675 | D21: 1350 | E21: Input: 10 kg wholesale
A22: Direct Profit | B22: =B20-B19 -> 39.5 | C22: =C20-C19 -> 197.5 | D22: =D20-D19 -> 395 | E22: MRP less cost
A23: Wholesale Profit | B23: =B21-B19 -> 9.5 | C23: =C21-C19 -> 47.5 | D23: =D21-D19 -> 95 | E23: Wholesale less cost
A24: Direct Margin % | B24: =SUM(Pricing_Profit_Analysis_3[1 kg Pack]) -> 474.5 | C24: =SUM(Pricing_Profit_Analysis_3[5 kg Pack]) -> 2372.5 | D24: =IFERROR(D22/D20,0) -> 0.23939394 | E24: Direct profit / MRP

Sheet High Protein
A1: Ingredient | B1: Ratio % | C1: 5 kg Qty | D1: 10 kg Qty | E1: Rate ₹/kg | F1: Cost — 5 kg | G1: Cost — 10 kg
C2: =B2*5 -> 0 | D2: =B2*10 -> 0 | E2: {=IFERROR(_xlfn.XLOOKUP(A2,tblPrices[Ingredient],tblPrices[Rate ₹/kg],0),0)} -> 0 | F2: =C2*E2 -> 0 | G2: =D2*E2 -> 0
A3: Whole Wheat (Sharbati Gehu) | B3: 0.6 | C3: =B3*5 -> 3 | D3: =B3*10 -> 6 | E3: {=IFERROR(_xlfn.XLOOKUP(A3,tblPrices[Ingredient],tblPrices[Rate ₹/kg],0),0)} -> 35 | F3: =C3*E3 -> 105 | G3: =D3*E3 -> 210 | I3: Metric | J3: Estimated Value | K3: Unit | L3: Note
A4: Soybean | B4: 0.15 | C4: =B4*5 -> 0.75 | D4: =B4*10 -> 1.5 | E4: {=IFERROR(_xlfn.XLOOKUP(A4,tblPrices[Ingredient],tblPrices[Rate ₹/kg],0),0)} -> 120 | F4: =C4*E4 -> 90 | G4: =D4*E4 -> 180 | I4: Energy (kcal) | J4: {=IFERROR(SUMPRODUCT($B$3:$B$8,_xlfn.XLOOKUP($A$3:$A$8,tblNutrients[Ingredient],tblNutrients[Energy kcal],0)),0)} -> 362.22 | K4: kcal | L4: Uses available reference data
A5: Premium Desi Kala Chana | B5: 0.12 | C5: =B5*5 -> 0.6 | D5: =B5*10 -> 1.2 | E5: {=IFERROR(_xlfn.XLOOKUP(A5,tblPrices[Ingredient],tblPrices[Rate ₹/kg],0),0)} -> 100 | F5: =C5*E5 -> 60 | G5: =D5*E5 -> 120 | I5: Protein (g) | J5: {=IFERROR(SUMPRODUCT($B$3:$B$8,_xlfn.XLOOKUP($A$3:$A$8,tblNutrients[Ingredient],tblNutrients[Protein g],0)),0)} -> 16.66 | K5: g | L5: Uses available reference data
A6: Premium Jau | B6: 0.08 | C6: =B6*5 -> 0.4 | D6: =B6*10 -> 0.8 | E6: {=IFERROR(_xlfn.XLOOKUP(A6,tblPrices[Ingredient],tblPrices[Rate ₹/kg],0),0)} -> 70 | F6: =C6*E6 -> 28 | G6: =D6*E6 -> 56 | I6: Carbohydrates (g) | J6: {=IFERROR(SUMPRODUCT($B$3:$B$8,_xlfn.XLOOKUP($A$3:$A$8,tblNutrients[Ingredient],tblNutrients[Carbohydrates g],0)),0)} -> 62.67 | K6: g | L6: Uses available reference data
A7: Flaxseed (Alsi) | B7: 0.03 | C7: =B7*5 -> 0.15 | D7: =B7*10 -> 0.3 | E7: {=IFERROR(_xlfn.XLOOKUP(A7,tblPrices[Ingredient],tblPrices[Rate ₹/kg],0),0)} -> 150 | F7: =C7*E7 -> 22.5 | G7: =D7*E7 -> 45 | I7: Total Sugars (g) | J7: {=IFERROR(SUMPRODUCT($B$3:$B$8,_xlfn.XLOOKUP($A$3:$A$8,tblNutrients[Ingredient],tblNutrients[Sugars g],0)),0)} -> 1.699 | K7: g | L7: Uses available reference data
A8: Psyllium Husk (Isabgol) | B8: 0.02 | C8: =B8*5 -> 0.1 | D8: =B8*10 -> 0.2 | E8: {=IFERROR(_xlfn.XLOOKUP(A8,tblPrices[Ingredient],tblPrices[Rate ₹/kg],0),0)} -> 150 | F8: =C8*E8 -> 15 | G8: =D8*E8 -> 30 | I8: Added Sugars (g) | J8: =0 -> 0 | K8: g | L8: Assumed zero
A9: Total Raw Material | B9: =SUM(B3:B8) -> 1 | C9: =SUM(C3:C8) -> 5 | D9: =SUM(D3:D8) -> 10 | F9: =SUM(F3:F8) -> 320.5 | G9: =SUM(G3:G8) -> 641 | I9: Total Fat (g) | J9: {=IFERROR(SUMPRODUCT($B$3:$B$8,_xlfn.XLOOKUP($A$3:$A$8,tblNutrients[Ingredient],tblNutrients[Fat g],0)),0)} -> 5.978 | K9: g | L9: Uses available reference data
A10: Milling & Roasting | E10: {=_xlfn.XLOOKUP("Milling & Roasting Cost",tblPrices[Ingredient],tblPrices[Rate ₹/kg],0)} -> 4 | F10: =5*E10 -> 20 | G10: =10*E10 -> 40 | I10: Saturated Fat (g) | J10: {=IFERROR(SUMPRODUCT($B$3:$B$8,_xlfn.XLOOKUP($A$3:$A$8,tblNutrients[Ingredient],tblNutrients[Sat Fat g],0)),0)} -> 0.825 | K10: g | L10: Uses available reference data
A11: Pouch Packaging | E11: {=_xlfn.XLOOKUP("3-Layer Laminated Pouch",tblPrices[Ingredient],tblPrices[Rate ₹/kg],0)} -> 5 | F11: =5*E11 -> 25 | G11: =10*E11 -> 50 | I11: Trans Fat (g) | J11: =0 -> 0 | K11: g | L11: Assumed zero
A12: Total Production Cost | E12: =SUM(Ingredient4[Rate ₹/kg]) -> 634 | F12: =SUM(F9:F11) -> 365.5 | G12: =SUM(G9:G11) -> 731 | I12: Dietary Fibre (g) | J12: {=IFERROR(SUMPRODUCT($B$3:$B$8,_xlfn.XLOOKUP($A$3:$A$8,tblNutrients[Ingredient],tblNutrients[Fibre g],0)),0)} -> 14.18 | K12: g | L12: Uses available reference data
I13: Sodium (mg) | J13: {=IFERROR(SUMPRODUCT($B$3:$B$8,_xlfn.XLOOKUP($A$3:$A$8,tblNutrients[Ingredient],tblNutrients[Sodium mg],0)),0)} -> 8.24 | K13: mg | L13: Uses available reference data
I14: Cholesterol (mg) | J14: =0 -> 0 | K14: mg | L14: Assumed zero
A18: Metric | B18: 1 kg Pack | C18: 5 kg Pack | D18: 10 kg Pack | E18: Notes
A19: Total Production Cost | B19: =G12/10 -> 73.1 | C19: =F12 -> 365.5 | D19: =G12 -> 731 | E19: Linked to recipe cost
A20: Retail Price (MRP) | B20: =D20/10 -> 135 | C20: =D20/2 -> 675 | D20: 1350 | E20: Input: 10 kg MRP
A21: Wholesale Price | B21: =D21/10 -> 115 | C21: =D21/2 -> 575 | D21: 1150 | E21: Input: 10 kg wholesale
A22: Direct Profit | B22: =B20-B19 -> 61.9 | C22: =C20-C19 -> 309.5 | D22: =D20-D19 -> 619 | E22: MRP less cost
A23: Wholesale Profit | B23: =B21-B19 -> 41.9 | C23: =C21-C19 -> 209.5 | D23: =D21-D19 -> 419 | E23: Wholesale less cost
A24: Direct Margin % | B24: =IFERROR(B22/B20,0) -> 0.45851852 | C24: =IFERROR(C22/C20,0) -> 0.45851852 | D24: =IFERROR(D22/D20,0) -> 0.45851852 | E24: Direct profit / MRP

Sheet Vitality Atta
A1: Ingredient | B1: Ratio % | C1: 5 kg Qty | D1: 10 kg Qty | E1: Rate ₹/kg | F1: Cost — 5 kg | G1: Cost — 10 kg
A2: Whole Wheat (Sharbati Gehu) | B2: 0.5 | C2: =B2*5 -> 2.5 | D2: =B2*10 -> 5 | E2: {=IFERROR(_xlfn.XLOOKUP(A2,tblPrices[Ingredient],tblPrices[Rate ₹/kg],0),0)} -> 35 | F2: =C2*E2 -> 87.5 | G2: =D2*E2 -> 175
A3: Premium Desi Kala Chana | B3: 0.15 | C3: =B3*5 -> 0.75 | D3: =B3*10 -> 1.5 | E3: {=IFERROR(_xlfn.XLOOKUP(A3,tblPrices[Ingredient],tblPrices[Rate ₹/kg],0),0)} -> 100 | F3: =C3*E3 -> 75 | G3: =D3*E3 -> 150 | I3: Metric | J3: Estimated Value | K3: Unit | L3: Note
A4: Premium Jau | B4: 0.1 | C4: =B4*5 -> 0.5 | D4: =B4*10 -> 1 | E4: {=IFERROR(_xlfn.XLOOKUP(A4,tblPrices[Ingredient],tblPrices[Rate ₹/kg],0),0)} -> 70 | F4: =C4*E4 -> 35 | G4: =D4*E4 -> 70 | I4: Energy (kcal) | J4: {=IFERROR(SUMPRODUCT($B$3:$B$8,_xlfn.XLOOKUP($A$3:$A$8,tblNutrients[Ingredient],tblNutrients[Energy kcal],0)),0)} -> 166.17 | K4: kcal | L4: Uses available reference data
A5: Ragi | B5: 0.1 | C5: =B5*5 -> 0.5 | D5: =B5*10 -> 1 | E5: {=IFERROR(_xlfn.XLOOKUP(A5,tblPrices[Ingredient],tblPrices[Rate ₹/kg],0),0)} -> 70 | F5: =C5*E5 -> 35 | G5: =D5*E5 -> 70 | I5: Protein (g) | J5: {=IFERROR(SUMPRODUCT($B$3:$B$8,_xlfn.XLOOKUP($A$3:$A$8,tblNutrients[Ingredient],tblNutrients[Protein g],0)),0)} -> 7.18 | K5: g | L5: Uses available reference data
A6: Pumpkin Seeds (Kaddu Beej) | B6: 0.05 | C6: =B6*5 -> 0.25 | D6: =B6*10 -> 0.5 | E6: {=IFERROR(_xlfn.XLOOKUP(A6,tblPrices[Ingredient],tblPrices[Rate ₹/kg],0),0)} -> 850 | F6: =C6*E6 -> 212.5 | G6: =D6*E6 -> 425 | I6: Carbohydrates (g) | J6: {=IFERROR(SUMPRODUCT($B$3:$B$8,_xlfn.XLOOKUP($A$3:$A$8,tblNutrients[Ingredient],tblNutrients[Carbohydrates g],0)),0)} -> 24.755 | K6: g | L6: Uses available reference data
A7: White Sesame Seeds (Til) | B7: 0.03 | C7: =B7*5 -> 0.15 | D7: =B7*10 -> 0.3 | E7: {=IFERROR(_xlfn.XLOOKUP(A7,tblPrices[Ingredient],tblPrices[Rate ₹/kg],0),0)} -> 250 | F7: =C7*E7 -> 37.5 | G7: =D7*E7 -> 75 | I7: Total Sugars (g) | J7: {=IFERROR(SUMPRODUCT($B$3:$B$8,_xlfn.XLOOKUP($A$3:$A$8,tblNutrients[Ingredient],tblNutrients[Sugars g],0)),0)} -> 0.63 | K7: g | L7: Uses available reference data
A8: Flaxseed (Alsi) | B8: 0.03 | C8: =B8*5 -> 0.15 | D8: =B8*10 -> 0.3 | E8: {=IFERROR(_xlfn.XLOOKUP(A8,tblPrices[Ingredient],tblPrices[Rate ₹/kg],0),0)} -> 150 | F8: =C8*E8 -> 22.5 | G8: =D8*E8 -> 45 | I8: Added Sugars (g) | J8: =0 -> 0 | K8: g | L8: Assumed zero
A9: Sunflower Seeds | B9: 0.02 | C9: =B9*5 -> 0.1 | D9: =B9*10 -> 0.2 | E9: {=IFERROR(_xlfn.XLOOKUP(A9,tblPrices[Ingredient],tblPrices[Rate ₹/kg],0),0)} -> 500 | F9: =C9*E9 -> 50 | G9: =D9*E9 -> 100 | I9: Total Fat (g) | J9: {=IFERROR(SUMPRODUCT($B$3:$B$8,_xlfn.XLOOKUP($A$3:$A$8,tblNutrients[Ingredient],tblNutrients[Fat g],0)),0)} -> 4.855 | K9: g | L9: Uses available reference data
A10: Methi Seeds (Fenugreek) | B10: 0.01 | C10: =B10*5 -> 0.05 | D10: =B10*10 -> 0.1 | E10: {=IFERROR(_xlfn.XLOOKUP(A10,tblPrices[Ingredient],tblPrices[Rate ₹/kg],0),0)} -> 0 | F10: =C10*E10 -> 0 | G10: =D10*E10 -> 0 | I10: Saturated Fat (g) | J10: {=IFERROR(SUMPRODUCT($B$3:$B$8,_xlfn.XLOOKUP($A$3:$A$8,tblNutrients[Ingredient],tblNutrients[Sat Fat g],0)),0)} -> 0.716 | K10: g | L10: Uses available reference data
A11: Psyllium Husk (Isabgol) | B11: 0.01 | C11: =B11*5 -> 0.05 | D11: =B11*10 -> 0.1 | E11: {=IFERROR(_xlfn.XLOOKUP(A11,tblPrices[Ingredient],tblPrices[Rate ₹/kg],0),0)} -> 150 | F11: =C11*E11 -> 7.5 | G11: =D11*E11 -> 15 | I11: Trans Fat (g) | J11: =0 -> 0 | K11: g | L11: Assumed zero
A12: Total Raw Material | B12: =SUM(B2:B11) -> 1 | C12: =SUM(C3:C8) -> 2.3 | D12: =SUM(D3:D8) -> 4.6 | F12: =SUM(F3:F8) -> 417.5 | G12: =SUM(G3:G8) -> 835 | I12: Dietary Fibre (g) | J12: {=IFERROR(SUMPRODUCT($B$3:$B$8,_xlfn.XLOOKUP($A$3:$A$8,tblNutrients[Ingredient],tblNutrients[Fibre g],0)),0)} -> 6.71 | K12: g | L12: Uses available reference data
A13: Milling & Roasting | E13: {=_xlfn.XLOOKUP("Milling & Roasting Cost",tblPrices[Ingredient],tblPrices[Rate ₹/kg],0)} -> 4 | F13: =5*E13 -> 20 | G13: =10*E13 -> 40 | I13: Sodium (mg) | J13: {=IFERROR(SUMPRODUCT($B$3:$B$8,_xlfn.XLOOKUP($A$3:$A$8,tblNutrients[Ingredient],tblNutrients[Sodium mg],0)),0)} -> 7.15 | K13: mg | L13: Uses available reference data
A14: Pouch Packaging | E14: {=_xlfn.XLOOKUP("3-Layer Laminated Pouch",tblPrices[Ingredient],tblPrices[Rate ₹/kg],0)} -> 5 | F14: =5*E14 -> 25 | G14: =10*E14 -> 50 | I14: Cholesterol (mg) | J14: =0 -> 0 | K14: mg | L14: Assumed zero
A15: Total Production Cost | F15: =SUM(F12:F14) + 50 -> 512.5 | G15: =SUM(G12:G14) + 50 -> 975
A21: Metric | B21: 1 kg Pack | C21: 5 kg Pack | D21: 10 kg Pack | E21: Notes
A22: Total Production Cost | B22: =G15/10 -> 97.5 | C22: =F15 -> 512.5 | D22: =G15 -> 975 | E22: Linked to recipe cost
A23: Retail Price (MRP) | B23: =D23/10 -> 135 | C23: =D23/2 -> 675 | D23: 1350 | E23: Input: 10 kg MRP
A24: Wholesale Price | B24: =D24/10 -> 115 | C24: =D24/2 -> 575 | D24: 1150 | E24: Input: 10 kg wholesale
A25: Direct Profit | B25: =B23-B22 -> 37.5 | C25: =C23-C22 -> 162.5 | D25: =D23-D22 -> 375 | E25: MRP less cost
A26: Wholesale Profit | B26: =B24-B22 -> 17.5 | C26: =C24-C22 -> 62.5 | D26: =D24-D22 -> 175 | E26: Wholesale less cost
A27: Direct Margin % | B27: =SUM(Table11[1 kg Pack]) -> 402.5 | C27: =SUM(Table11[5 kg Pack]) -> 1987.5 | D27: =IFERROR(D25/D23,0) -> 0.27777778 | E27: Direct profit / MRP

Sheet My Choice
A1: Ingredient | B1: Ratio % | C1: 5 kg Qty | D1: 10 kg Qty | E1: Rate ₹/kg | F1: Cost — 5 kg | G1: Cost — 10 kg
C2: =B2*5 -> 0 | D2: =B2*10 -> 0 | E2: {=IFERROR(_xlfn.XLOOKUP(A2,tblPrices[Ingredient],tblPrices[Rate ₹/kg],0),0)} -> 0 | F2: =C2*E2 -> 0 | G2: =D2*E2 -> 0 | I2: Metric | J2: Estimated Value | K2: Unit | L2: Note
C3: =B3*5 -> 0 | D3: =B3*10 -> 0 | E3: {=IFERROR(_xlfn.XLOOKUP(A3,tblPrices[Ingredient],tblPrices[Rate ₹/kg],0),0)} -> 0 | F3: =C3*E3 -> 0 | G3: =D3*E3 -> 0 | I3: Energy (kcal) | J3: {=IFERROR(SUMPRODUCT($B$2:$B$9,_xlfn.XLOOKUP($A$2:$A$9,tblNutrients[Ingredient],tblNutrients[Energy kcal],0)),0)} -> 0 | K3: kcal | L3: Uses available reference data
C4: =B4*5 -> 0 | D4: =B4*10 -> 0 | E4: {=IFERROR(_xlfn.XLOOKUP(A4,tblPrices[Ingredient],tblPrices[Rate ₹/kg],0),0)} -> 0 | F4: =C4*E4 -> 0 | G4: =D4*E4 -> 0 | I4: Protein (g) | J4: {=IFERROR(SUMPRODUCT($B$2:$B$9,_xlfn.XLOOKUP($A$2:$A$9,tblNutrients[Ingredient],tblNutrients[Protein g],0)),0)} -> 0 | K4: g | L4: Uses available reference data
C5: =B5*5 -> 0 | D5: =B5*10 -> 0 | E5: {=IFERROR(_xlfn.XLOOKUP(A5,tblPrices[Ingredient],tblPrices[Rate ₹/kg],0),0)} -> 0 | F5: =C5*E5 -> 0 | G5: =D5*E5 -> 0 | I5: Carbohydrates (g) | J5: {=IFERROR(SUMPRODUCT($B$2:$B$9,_xlfn.XLOOKUP($A$2:$A$9,tblNutrients[Ingredient],tblNutrients[Carbohydrates g],0)),0)} -> 0 | K5: g | L5: Uses available reference data
C6: =B6*5 -> 0 | D6: =B6*10 -> 0 | E6: {=IFERROR(_xlfn.XLOOKUP(A6,tblPrices[Ingredient],tblPrices[Rate ₹/kg],0),0)} -> 0 | F6: =C6*E6 -> 0 | G6: =D6*E6 -> 0 | I6: Total Sugars (g) | J6: {=IFERROR(SUMPRODUCT($B$2:$B$9,_xlfn.XLOOKUP($A$2:$A$9,tblNutrients[Ingredient],tblNutrients[Sugars g],0)),0)} -> 0 | K6: g | L6: Uses available reference data
C7: =B7*5 -> 0 | D7: =B7*10 -> 0 | E7: {=IFERROR(_xlfn.XLOOKUP(A7,tblPrices[Ingredient],tblPrices[Rate ₹/kg],0),0)} -> 0 | F7: =C7*E7 -> 0 | G7: =D7*E7 -> 0 | I7: Added Sugars (g) | J7: =0 -> 0 | K7: g | L7: Assumed zero
C8: =B8*5 -> 0 | D8: =B8*10 -> 0 | E8: {=IFERROR(_xlfn.XLOOKUP(A8,tblPrices[Ingredient],tblPrices[Rate ₹/kg],0),0)} -> 0 | F8: =C8*E8 -> 0 | G8: =D8*E8 -> 0 | I8: Total Fat (g) | J8: {=IFERROR(SUMPRODUCT($B$2:$B$9,_xlfn.XLOOKUP($A$2:$A$9,tblNutrients[Ingredient],tblNutrients[Fat g],0)),0)} -> 0 | K8: g | L8: Uses available reference data
C9: =B9*5 -> 0 | D9: =B9*10 -> 0 | E9: {=IFERROR(_xlfn.XLOOKUP(A9,tblPrices[Ingredient],tblPrices[Rate ₹/kg],0),0)} -> 0 | F9: =C9*E9 -> 0 | G9: =D9*E9 -> 0 | I9: Saturated Fat (g) | J9: {=IFERROR(SUMPRODUCT($B$2:$B$9,_xlfn.XLOOKUP($A$2:$A$9,tblNutrients[Ingredient],tblNutrients[Sat Fat g],0)),0)} -> 0 | K9: g | L9: Uses available reference data
A10: Total Raw Material | B10: =SUM(B2:B9) -> 0 | C10: =SUM(C2:C9) -> 0 | D10: =SUM(D2:D9) -> 0 | F10: =SUM(F2:F9) -> 0 | G10: =SUM(G2:G9) -> 0 | I10: Trans Fat (g) | J10: =0 -> 0 | K10: g | L10: Assumed zero
A11: Milling & Roasting | E11: {=_xlfn.XLOOKUP("Milling & Roasting Cost",tblPrices[Ingredient],tblPrices[Rate ₹/kg],0)} -> 4 | F11: =5*E11 -> 20 | G11: =10*E11 -> 40 | I11: Dietary Fibre (g) | J11: {=IFERROR(SUMPRODUCT($B$2:$B$9,_xlfn.XLOOKUP($A$2:$A$9,tblNutrients[Ingredient],tblNutrients[Fibre g],0)),0)} -> 0 | K11: g | L11: Uses available reference data
A12: Pouch Packaging | E12: {=_xlfn.XLOOKUP("3-Layer Laminated Pouch",tblPrices[Ingredient],tblPrices[Rate ₹/kg],0)} -> 5 | F12: =5*E12 -> 25 | G12: =10*E12 -> 50 | I12: Sodium (mg) | J12: {=IFERROR(SUMPRODUCT($B$2:$B$9,_xlfn.XLOOKUP($A$2:$A$9,tblNutrients[Ingredient],tblNutrients[Sodium mg],0)),0)} -> 0 | K12: mg | L12: Uses available reference data
A13: Total Production Cost | E13: =SUM(my_choice[Rate ₹/kg]) -> 9 | F13: =SUM(F10:F12) -> 45 | G13: =SUM(G10:G12) -> 90 | I13: Cholesterol (mg) | J13: =0 -> 0 | K13: mg | L13: Assumed zero
A16: Metric | B16: 1 kg Pack | C16: 5 kg Pack | D16: 10 kg Pack | E16: Notes
A17: Total Production Cost | B17: =G13/10 -> 9 | C17: =F13 -> 45 | D17: =G13 -> 90 | E17: Linked to recipe cost
A18: Retail Price (MRP) | B18: =D18/10 -> 95 | C18: =D18/2 -> 475 | D18: 950 | E18: Input: 10 kg MRP
A19: Wholesale Price | B19: =D19/10 -> 76 | C19: =D19/2 -> 380 | D19: 760 | E19: Input: 10 kg wholesale
A20: Direct Profit | B20: =B18-B17 -> 86 | C20: =C18-C17 -> 430 | D20: =D18-D17 -> 860 | E20: MRP less cost
A21: Wholesale Profit | B21: =B19-B17 -> 67 | C21: =C19-C17 -> 335 | D21: =D19-D17 -> 670 | E21: Wholesale less cost
A22: Direct Margin % | B22: =SUM(Table2[1 kg Pack]) -> 333 | C22: =SUM(Table2[5 kg Pack]) -> 1665 | D22: =IFERROR(D20/D18,0) -> 0.90526316 | E22: Direct profit / MRP

Sheet Dashboard
A1: Product Name | B1: Raw Cost (10 kg) | C1: Total Cost (10 kg) | D1: MRP (10 kg) | E1: Wholesale Price (10 kg) | F1: Direct Profit (10 kg) | G1: Wholesale Profit (10 kg) | H1: Direct Margin % | I1: Mesho Pricefor 10 Kg
A2: ArogyaBhog Everyday Atta | B2: ='Everyday Atta'!G13 -> 556.5 | C2: ='Everyday Atta'!G13 -> 556.5 | D2: ='Everyday Atta'!D18 -> 950 | E2: ='Everyday Atta'!D19 -> 760 | F2: ='Everyday Atta'!D20 -> 393.5 | G2: ='Everyday Atta'!D21 -> 203.5 | H2: ='Everyday Atta'!D22 -> 0.41421053 | I2: =B2*2 -> 1113
A3: ArogyaBhog Sugar Care Atta | B3: ='Sugar Care'!G14 -> 706 | C3: ='Sugar Care'!G14 -> 706 | D3: ='Sugar Care'!D19 -> 1250 | E3: ='Sugar Care'!D20 -> 1000 | F3: ='Sugar Care'!D21 -> 544 | G3: ='Sugar Care'!D22 -> 294 | H3: ='Sugar Care'!D23 -> 0.4352 | I3: =B3*2 -> 1412
A4: ArogyaBhog Thyro-Care Atta | B4: ='Thyro Care'!G12 -> 1255 | C4: ='Thyro Care'!G12 -> 1255 | D4: ='Thyro Care'!D20 -> 1650 | E4: ='Thyro Care'!D21 -> 1350 | F4: ='Thyro Care'!D22 -> 395 | G4: ='Thyro Care'!D23 -> 95 | H4: ='Thyro Care'!D24 -> 0.23939394 | I4: =B4*2 -> 2510
A5: ArogyaBhog High-Protein Fitness Atta | B5: ='High Protein'!G12 -> 731 | C5: ='High Protein'!G12 -> 731 | D5: ='High Protein'!D20 -> 1350 | E5: ='High Protein'!D21 -> 1150 | F5: ='High Protein'!D22 -> 619 | G5: ='High Protein'!D23 -> 419 | H5: ='High Protein'!D24 -> 0.45851852 | I5: =B5*2 -> 1462
A6: ArogyaBhog Vitality Atta | B6: ='Vitality Atta'!G15 -> 975 | C6: ='Vitality Atta'!G15 -> 975 | D6: ='Vitality Atta'!I10 -> Saturated Fat (g) | E6: ='Vitality Atta'!J10 -> 0.716 | F6: ='Vitality Atta'!K10 -> g | G6: ='Vitality Atta'!L10 -> Uses available reference data | H6: ='Vitality Atta'!M10 | I6: =B6*2 -> 1950
A7: ArogyaBhog My-Choice atta | B7: ='Vitality Atta'!G16 | C7: ='Vitality Atta'!G16 | D7: ='Vitality Atta'!I11 -> Trans Fat (g) | E7: ='Vitality Atta'!J11 -> 0 | F7: ='Vitality Atta'!K11 -> g | G7: ='Vitality Atta'!L11 -> Assumed zero | H7: ='Vitality Atta'!M11 | I7: =B7*2 -> 0
A10: Blend Name | B10: Raw Cost / kg | C10: Selling Rate / kg | D10: 5 kg Bag Price | E10: Selling price of 5 Kg | F10: 10 kg Bag Price | G10: Selling price of 10 Kg
A11: 1. ArogyaBhog Everyday Atta (General Health) | B11: ₹40.50 | C11: ₹55.00 | D11: ₹275 | E11: 320 / 380 | F11: =ROUNDUP('Everyday Atta'!G13,0) -> 557 | G11: 600 / 650
A12: 2. ArogyaBhog Sugar Care Atta (Diabetic Support) | B12: ₹50.20 | C12: ₹65.00 | D12: ₹325 | E12: 380 / 400 | F12: ='Sugar Care'!G14 -> 706 | G12: 720 / 800
A13: 3. ArogyaBhog High-Protein Fitness Atta | B13: ₹53.70 | C13: ₹70.00 | D13: ₹350 | E13: 400 / 450 | F13: ='High Protein'!G12 -> 731 | G13: 750 / 900
A14: 4. ArogyaBhog Thyro-Care Atta (100% Soy-Free) | B14: ₹110.50 | C14: ₹130.00 | D14: ₹650 | E14: 700 / 800 | F14: ='Thyro Care'!G12 -> 1255 | G14: 1350 / 1500
A15: 5. ArogyaBhog Vitality Atta (Hormonal & Seeds) | B15: ₹85.60 | C15: ₹105.00 | D15: ₹525 | E15: 600 / 750 | F15: ='Vitality Atta'!G15 -> 975 | G15: 1100 / 1400
